movoid_debug/__init__.py
movoid_debug/simple_debug.py
movoid_debug/simple_hot_pause.py
movoid_debug/flow/__init__.py
movoid_debug/flow/code.py
movoid_debug/flow/flow.py
movoid_debug/flow/log.py
movoid_debug/flow/traceback.py
movoid_debug/simple_ui/__init__.py
movoid_debug/simple_ui/basic.py
movoid_debug/simple_ui/flow_thread.py
movoid_debug/simple_ui/frame_main.py
movoid_debug/simple_ui/main_window.py
movoid_debug/simple_ui/value_set_window.py
movoid_debug-1.5.5.dist-info/METADATA
movoid_debug-1.5.5.dist-info/WHEEL
movoid_debug-1.5.5.dist-info/top_level.txt
movoid_debug-1.5.5.dist-info/RECORD
