Metadata-Version: 2.4
Name: movoid_debug
Version: 1.5.5
Home-page: 
Author: movoid
Author-email: bobrobotsun@163.com
Requires-Dist: movoid_config
Requires-Dist: movoid_log
Requires-Dist: movoid_function>=1.8.0
Provides-Extra: debug
Requires-Dist: pyside6; extra == "debug"
Requires-Dist: requests; extra == "debug"
Dynamic: author
Dynamic: author-email
Dynamic: description
Dynamic: description-content-type
Dynamic: provides-extra
Dynamic: requires-dist
